[
  {
    "user_id": "30924032227244032",
    "question": "mã ngành của ngành nha khoa",
    "answer": "Mã ngành của ngành Răng-Hàm-Mặt (Nha khoa) là 7720501.",
    "timestamp": "2025-09-25T12:53:53.693Z"
  },
  {
    "user_id": "30924032227244032",
    "question": "học phí của nha khoa",
    "answer": "Chuyên ngành Bác sĩ Răng - Hàm - Mặt có học phí là 3.090.000 VNĐ/tháng, 49.200.000 VNĐ/kỳ và 98.880.000 VNĐ/năm.",
    "timestamp": "2025-09-25T13:25:48.178Z"
  },
  {
    "user_id": "30924032227244032",
    "question": "học phí của ngành khoa học máy tinh",
    "answer": "Để biết học phí của ngành Khoa học Máy tính, bạn cần cung cấp thêm thông tin về chương trình đào tạo mà bạn quan tâm (ví dụ: chương trình đại trà, chương trình tài năng, chương trình quốc tế...). Mỗi chương trình sẽ có mức học phí khác nhau.",
    "timestamp": "2025-09-25T16:20:59.843Z"
  }
]